{"nodes": [{"identifier": "4de36eab-3ff0-4e6c-b40b-8e0a99c346b1", "node_type": "exception_node", "stamp": {"step": 1, "time": 1753146180.347927, "identifier": "Finished executing exception_node"}, "details": {"internals": {"latency": {"total_time": 0.0009999275207519531}}}, "parent": {"identifier": "4de36eab-3ff0-4e6c-b40b-8e0a99c346b1", "node_type": "exception_node", "stamp": {"step": 0, "time": 1753146180.3469272, "identifier": "START CREATED exception_node"}, "details": {"internals": {}}, "parent": null}}], "edges": [{"source": null, "target": "4de36eab-3ff0-4e6c-b40b-8e0a99c346b1", "identifier": "bf58123a-b6c7-40a5-a1dd-fb3d92d4312a", "stamp": {"step": 1, "time": 1753146180.347927, "identifier": "Finished executing exception_node"}, "details": {"state": "Completed", "input_args": [], "input_kwargs": {}, "output": "ERROR: w/ type <class 'requestcompletion.state.request.Failure'><requestcompletion.state.request.Failure object at 0x000002572B2716F0>"}, "parent": {"source": null, "target": "4de36eab-3ff0-4e6c-b40b-8e0a99c346b1", "identifier": "bf58123a-b6c7-40a5-a1dd-fb3d92d4312a", "stamp": {"step": 0, "time": 1753146180.3469272, "identifier": "START CREATED exception_node"}, "details": {"state": "Open", "input_args": [], "input_kwargs": {}, "output": null}, "parent": null}}], "steps": [{"step": 0, "time": 1753146180.3469272, "identifier": "START CREATED exception_node"}, {"step": 1, "time": 1753146180.347927, "identifier": "Finished executing exception_node"}]}