{"nodes": [{"identifier": "3031bf59-6cd8-4b5f-a8a8-36bfb0ee285f", "node_type": "slow_rng", "stamp": {"step": 1, "time": 1753146181.201275, "identifier": "Finished executing slow_rng"}, "details": {"internals": {"latency": {"total_time": 0.21473097801208496}}}, "parent": {"identifier": "3031bf59-6cd8-4b5f-a8a8-36bfb0ee285f", "node_type": "slow_rng", "stamp": {"step": 0, "time": 1753146180.9854562, "identifier": "START CREATED slow_rng"}, "details": {"internals": {}}, "parent": null}}], "edges": [{"source": null, "target": "3031bf59-6cd8-4b5f-a8a8-36bfb0ee285f", "identifier": "546fbe4b-298b-4a23-a247-e3d71809519b", "stamp": {"step": 1, "time": 1753146181.201275, "identifier": "Finished executing slow_rng"}, "details": {"state": "Completed", "input_args": [0.2], "input_kwargs": {}, "output": 0.7942078573249607}, "parent": {"source": null, "target": "3031bf59-6cd8-4b5f-a8a8-36bfb0ee285f", "identifier": "546fbe4b-298b-4a23-a247-e3d71809519b", "stamp": {"step": 0, "time": 1753146180.9854562, "identifier": "START CREATED slow_rng"}, "details": {"state": "Open", "input_args": [0.2], "input_kwargs": {}, "output": null}, "parent": null}}], "steps": [{"step": 0, "time": 1753146180.9854562, "identifier": "START CREATED slow_rng"}, {"step": 1, "time": 1753146181.201275, "identifier": "Finished executing slow_rng"}]}